pagemaker/__init__.py
pagemaker/cli.py
pagemaker/fonts.py
pagemaker/generator.py
pagemaker/parser.py
pagemaker/table_render.py
pagemaker/validation.py
pagemaker/fonts/Crimson_Pro/CrimsonPro-Italic-VariableFont_wght.ttf
pagemaker/fonts/Crimson_Pro/CrimsonPro-VariableFont_wght.ttf
"pagemaker/fonts/Inter/Inter-Italic-VariableFont_opsz,wght.ttf"
"pagemaker/fonts/Inter/Inter-VariableFont_opsz,wght.ttf"
pagemaker/fonts/JetBrains_Mono/JetBrainsMono-VariableFont_wght.ttf
pagemaker/generation/__init__.py
pagemaker/generation/core.py
pagemaker/generation/elements.py
pagemaker/generation/layout.py
pagemaker/generation/media_renderer.py
pagemaker/generation/media_sizing.py
pagemaker/generation/pdf_postprocess.py
pagemaker/generation/pdf_processor.py
pagemaker/utils/__init__.py
pagemaker/utils/alignment.py
pagemaker/utils/assets_paths.py
pagemaker/utils/file_ops.py
pagemaker/utils/font_discovery.py
pagemaker/utils/typst_helpers.py
typst_pagemaker-0.1.19.dist-info/licenses/LICENSE
typst_pagemaker-0.1.19.dist-info/METADATA
typst_pagemaker-0.1.19.dist-info/WHEEL
typst_pagemaker-0.1.19.dist-info/entry_points.txt
typst_pagemaker-0.1.19.dist-info/top_level.txt
typst_pagemaker-0.1.19.dist-info/RECORD
