Metadata-Version: 2.4
Name: typst-pagemaker
Version: 0.1.19
Summary: Structured document-to-page layout system for Typst with explicit positioning and professional typography
Author: Project
License-Expression: MIT
Project-URL: Homepage, https://github.com/sanderboer/typst-pagemaker
Project-URL: Repository, https://github.com/sanderboer/typst-pagemaker
Project-URL: Issues, https://github.com/sanderboer/typst-pagemaker/issues
Keywords: typst,orgmode,layout,grid,slides,pdf
Classifier: Development Status :: 3 - Alpha
Classifier: Intended Audience :: Developers
Classifier: Topic :: Text Processing :: Markup
Classifier: Topic :: Office/Business :: Office Suites
Classifier: Topic :: Multimedia :: Graphics :: Presentation
Classifier: Programming Language :: Python :: 3
Classifier: Programming Language :: Python :: 3.9
Classifier: Programming Language :: Python :: 3.10
Classifier: Programming Language :: Python :: 3.11
Classifier: Programming Language :: Python :: 3.12
Classifier: Operating System :: OS Independent
Requires-Python: >=3.9
License-File: LICENSE
Requires-Dist: fontdownloader
Requires-Dist: fonttools>=4.0
Dynamic: license-file
